microtc/__init__.py
microtc/command_line.py
microtc/emoticons.py
microtc/params.py
microtc/regscorewrapper.py
microtc/scorewrapper.py
microtc/textmodel.py
microtc/utils.py
microtc/weighting.py
microtc/wrappers.py
microtc/resources/emojis.json.gz
microtc/resources/emoticons.json
microtc/tests/__init__.py
microtc/tests/test_classifier.py
microtc/tests/test_command_line.py
microtc/tests/test_emoticons.py
microtc/tests/test_textmodel.py
microtc/tests/test_utils.py
microtc/tests/test_weighting.py
microtc/tests/text.json
microtc/tools/microtc-ensemble
microtc/tools/microtc-kfolds
microtc/tools/microtc-params
microtc/tools/microtc-perf
microtc/tools/microtc-predict
microtc/tools/microtc-retrain
microtc/tools/microtc-textModel
microtc/tools/microtc-train
microtc-2.4.13.data/scripts/microtc-ensemble
microtc-2.4.13.data/scripts/microtc-kfolds
microtc-2.4.13.data/scripts/microtc-params
microtc-2.4.13.data/scripts/microtc-perf
microtc-2.4.13.data/scripts/microtc-predict
microtc-2.4.13.data/scripts/microtc-retrain
microtc-2.4.13.data/scripts/microtc-textModel
microtc-2.4.13.data/scripts/microtc-train
microtc-2.4.13.dist-info/LICENSE
microtc-2.4.13.dist-info/METADATA
microtc-2.4.13.dist-info/WHEEL
microtc-2.4.13.dist-info/top_level.txt
microtc-2.4.13.dist-info/RECORD
